suffixdg/__init__.py
suffixdg/main.py
suffixdg-0.0.1.dist-info/LICENSE.md
suffixdg-0.0.1.dist-info/METADATA
suffixdg-0.0.1.dist-info/WHEEL
suffixdg-0.0.1.dist-info/top_level.txt
suffixdg-0.0.1.dist-info/RECORD
